deepleaps/__init__.py
deepleaps/app/Exceptions.py
deepleaps/app/Format.py
deepleaps/app/__init__.py
deepleaps/app/app.py
deepleaps/app/default_config.yaml
deepleaps/dataloader/DataLoader.py
deepleaps/dataloader/Dataset.py
deepleaps/dataloader/TensorTypes.py
deepleaps/dataloader/Transform.py
deepleaps/dataloader/__init__.py
deepleaps/dataloader/transforms.py
deepleaps/ipc/RW_lock.py
deepleaps/ipc/RunningCommand.py
deepleaps/ipc/RunningGraphController.py
deepleaps/ipc/RunningModuleVisualizer.py
deepleaps/ipc/ThreadCommand.py
deepleaps/ipc/__init__.py
deepleaps/model/BaseModel.py
deepleaps/model/__init__.py
deepleaps/trainer/ModelController.py
deepleaps/trainer/TrainerContainer.py
deepleaps/trainer/TrainerModule.py
deepleaps/trainer/__init__.py
deepleaps/trainer/losses.py
deepleaps/trainer/optimizer.py
deepleaps/utils/__init__.py
deepleaps/utils/config.py
deepleaps/utils/data_structure.py
deepleaps/utils/file_struct.py
deepleaps/utils/runtime.py
deepleaps/workspace/client.py
deepleaps/workspace/main.py
deepleaps/workspace/exampleDataset/0000.jpg
deepleaps/workspace/exampleDataset/0001.jpg
deepleaps/workspace/exampleDataset/0002.jpg
deepleaps/workspace/resource/configs/default.yaml
deepleaps/workspace/resource/configs/command/default_runnable_command.yaml
deepleaps/workspace/resource/configs/dataloader/exampleDataLoader.yaml
deepleaps/workspace/resource/configs/dataset/Example.yaml
deepleaps/workspace/resource/configs/ipc/default_runnable_command.yaml
deepleaps/workspace/resource/configs/model/SimpleLayerModel.yaml
deepleaps/workspace/resource/configs/trainer/ExampleContainer.yaml
deepleaps/workspace/resource/configs/trainer/ExampleController.yaml
deepleaps/workspace/resource/output/README.md
deepleaps/workspace/src/dataloader/Exampledataset.py
deepleaps/workspace/src/dataloader/TensorTypes.py
deepleaps/workspace/src/dataloader/transforms.py
deepleaps/workspace/src/dataloader/__pycache__/Exampledataset.cpython-37.pyc
deepleaps/workspace/src/ipc/CustomCommand.py
deep_leaps-0.0.14.dist-info/LICENSE.md
deep_leaps-0.0.14.dist-info/METADATA
deep_leaps-0.0.14.dist-info/WHEEL
deep_leaps-0.0.14.dist-info/top_level.txt
deep_leaps-0.0.14.dist-info/RECORD
