Metadata-Version: 2.1
Name: deep-leaps
Version: 0.0.14
Summary: Data driven development based deep learning deepleaps(pytorch)
Home-page: https://github.com/Longseabear/deep-leaps-pytorch.git
Author: Leaps
Author-email: leap1568@gmail.com
License: UNKNOWN
Platform: UNKNOWN
Classifier: Programming Language :: Python :: 3
Classifier: License :: OSI Approved :: MIT License
Classifier: Operating System :: OS Independent
Requires-Dist: numpy (==1.16.4)
Requires-Dist: scipy (==1.0.1)
Requires-Dist: torch (==1.4.0)
Requires-Dist: tqdm (==4.46.0)
Requires-Dist: pyparsing (==2.4.7)
Requires-Dist: matplotlib (==3.1.3)
Requires-Dist: PyYAML (==5.4.1)
Requires-Dist: Pillow (==5.1.0)
